{"id":"OP15-006","pack_id":"563115","name":"Cavendish","rarity":"Uncommon","category":"Character","img_url":"../images/cardlist/card/OP15-006.png?251223","img_full_url":"https://asia-th.onepiece-cardgame.com/images/cardlist/card/OP15-006.png?251223","cost":4,"attributes":["Slash"],"power":4000,"counter":2000,"colors":["Red"],"block_number":4,"types":["เดรสโรซ่า","กลุ่มโจรสลัดงดงาม"],"effect":"ถ้ามี อีเวนต์ อยู่ในแทรชของเรา จำนวน 4 ใบ หรือมากกว่าละก็, คาแรกเตอร์นี้ จะพาวเวอร์ +2000.","trigger":null}