{"id":"OP15-028","pack_id":"622115","name":"Les frères Nyaban","rarity":"Uncommon","category":"Character","img_url":"../images/cardlist/card/OP15-028.webp?260428","img_full_url":"https://fr.onepiece-cardgame.com/images/cardlist/card/OP15-028.webp?260428","cost":1,"attributes":["Slash"],"power":2000,"counter":2000,"colors":["Green"],"block_number":4,"types":["East Blue","Équipage du Chat noir"],"effect":"[Jouée] Si votre Leader est de type {East Blue}, donnez jusqu'à 1 carte DON!! de la zone de Coût de votre adversaire à 1 Personnage adverse.","trigger":null}