{"id":"EB04-014","pack_id":"563204","name":"Kouzuki Sukiyaki","rarity":"Common","category":"Character","img_url":"../images/cardlist/card/EB04-014.png?251223","img_full_url":"https://asia-th.onepiece-cardgame.com/images/cardlist/card/EB04-014.png?251223","cost":3,"attributes":["Wisdom"],"power":null,"counter":null,"colors":["Green"],"block_number":4,"types":["วาโนะคุนิ","ตระกูลโคสึกิ"],"effect":"[บล็อกเกอร์] (ขณะที่คู่แข่งโจมตี, จะสามารถ เรสต์ การ์ดใบนี้, และเปลี่ยนเป้าหมายการโจมตีมาที่การ์ดใบนี้)<br>[สั่งใช้ : เมน] [เทิร์นละ 1 ครั้ง] นำ ด้ง!! ที่เรสต์อยู่ จำนวนไม่เกิน 1 ใบ, ใส่ให้ ลีดเดอร์ของฝ่ายเรา ที่มีคุณสมบัติ &lt; วาโนะคุนิ &gt;.","trigger":null}